[
    {
        "id": 1,
        "name": "Alice Smith",
        "age": 25,
        "email": "alice.smith@example.com",
        "phone_number": "+1 (555) 555-5555",
        "full_address": "123 Main St.",
        "city": "Anytown",
        "province": "State",
        "postalcode": "12345",
        "country": "USA",
        "active": true
    },
    {
        "id": 2,
        "name": "Bob Johnson",
        "age": 32,
        "email": "bob.johnson@example.com",
        "phone_number": "+1 (555) 555-5555",
        "full_address": "456 Elm St.",
        "city": "Anytown",
        "province": "State",
        "postalcode": "12345",
        "country": "USA",
        "active": true
    },
    {
        "id": 3,
        "name": "Charlie Lee",
        "age": 45,
        "email": "charlie.lee@example.com",
        "phone_number": "+1 (555) 555-5555",
        "full_address": "789 Oak St.",
        "city": "Anytown",
        "province": "State",
        "postalcode": "12345",
        "country": "USA",
        "active": true
    },
    {
        "id": 4,
        "name": "David Chen",
        "age": 28,
        "email": "david.chen@example.com",
        "phone_number": "+1 (555) 555-5555",
        "full_address": "321 Pine St.",
        "city": "Anytown",
        "province": "State",
        "postalcode": "12345",
        "country": "USA",
        "active": true
    },
    {   
        "id": 5,
        "name": "Emily Davis",
        "age": 31,
        "email": "emily.davis@example.com",
        "phone_number": "+1 (555) 555-5555",
        "full_address": "654 Cedar St.",
        "city": "Anytown",
        "province": "State",
        "postalcode": "12345",
        "country": "USA",
        "active": true
    },
    {
        "id": 6,
        "name": "Frank Wilson",
        "age": 40,
        "email": "frank.wilson@example.com",
        "phone_number": "+1 (555) 555-5555",
        "full_address": "987 Maple St.",
        "city": "Anytown",
        "province": "State",
        "postalcode": "12345",
        "country": "USA",
        "active": true
    },
    {
        "id": 7,
        "name": "Grace Taylor",
        "age": 26,
        "email": "grace.taylor@example.com",
        "phone_number": "+1 (555) 555-5555",
        "full_address": "159 Walnut St.",
        "city": "Anytown",
        "province": "State",
        "postalcode": "12345",
        "country": "USA",
        "active": true
    },
    {
        "id": 8,
        "name": "Henry Lee",
        "age": 37,
        "email": "henry.lee@example.com",
        "phone_number": "+1 (555) 555-5555",
        "full_address": "321 Oak St.",
        "city": "Anytown",
        "province": "State",
        "postalcode": "12345",
        "country": "USA",
        "active": true
    },
    {
        "id": 9,
        "name": "Isabella Garcia",
        "age": 29,
        "email": "isabella.garcia@example.com",
        "phone_number": "+1 (555) 555-5555",
        "full_address": "654 Pine St.",
        "city": "Anytown",
        "province": "State",
        "postalcode": "12345",
        "country": "USA",
        "active": true
    },
    {
        "id": 10,
        "name": "Jackie Chan",
        "age": 57,
        "email": "jackie.chan@example.com",
        "phone_number": "+1 (555) 555-5555",
        "full_address": "987 Cedar St.",
        "city": "Anytown",
        "province": "State",
        "postalcode": "12345",
        "country": "USA",
        "active": true
    },
    {
        "id": 11,
        "name": "Katherine Lee",
        "age": 23,
        "email": "katherine.lee@example.com",
        "phone_number": "+1 (555) 555-5555",
        "full_address": "159 Maple St.",
        "city": "Anytown",
        "province": "State",
        "postalcode": "12345",
        "country": "USA",
        "active": true
    },
    {
        "id": 12,
        "name": "Liam Johnson",
        "age": 35,
        "email": "liam.johnson@example.com",
        "phone_number": "+1 (555) 555-5555",
        "full_address": "753 Walnut St.",
        "city": "Anytown",
        "province": "State",
        "postalcode": "12345",
        "country": "USA",
        "active": true
    },  {
        "id": 13,
        "name": "Isabella Johnson",
        "age": 29,
        "email": "isabella.johnson@example.com",
        "phone_number": "+1 (555) 555-5555",
        "full_address": "987 Oak St.",
        "city": "Anytown",
        "province": "State",
        "postalcode": "12345",
        "country": "USA",
        "active": true
      },
      {
        "id": 14,
        "name": "Jack Hernandez",
        "age": 38,
        "email": "jack.hernandez@example.com",
        "phone_number": "+1 (555) 555-5555",
        "full_address": "654 Pine St.",
        "city": "Anytown",
        "province": "State",
        "postalcode": "12345",
        "country": "USA",
        "active": true
      },
      {
        "id": 15,
        "name": "Katherine Lee",
        "age": 33,
        "email": "katherine.lee@example.com",
        "phone_number": "+1 (555) 555-5555",
        "full_address": "321 Cedar St.",
        "city": "Anytown",
        "province": "State",
        "postalcode": "12345",
        "country": "USA",
        "active": true
      },
      {
        "id": 16,
        "name": "Lucas Chen",
        "age": 42,
        "email": "lucas.chen@example.com",
        "phone_number": "+1 (555) 555-5555",
        "full_address": "789 Walnut St.",
        "city": "Anytown",
        "province": "State",
        "postalcode": "12345",
        "country": "USA",
        "active": true
      },
      {
        "id": 17,
        "name": "Madison Wilson",
        "age": 27,
        "email": "madison.wilson@example.com",
        "phone_number": "+1 (555) 555-5555",
        "full_address": "456 Maple St.",
        "city": "Anytown",
        "province": "State",
        "postalcode": "12345",
        "country": "USA",
        "active": true
      },
      {
        "id": 18,
        "name": "Nathan Taylor",
        "age": 39,
        "email": "nathan.taylor@example.com",
        "phone_number": "+1 (555) 555-5555",
        "full_address": "123 Elm St.",
        "city": "Anytown",
        "province": "State",
        "postalcode": "12345",
        "country": "USA",
        "active": true
      },
      {
        "id": 19,
        "name": "Olivia Davis",
        "age": 30,
        "email": "olivia.davis@example.com",
        "phone_number": "+1 (555) 555-5555",
        "full_address": "789 Cedar St.",
        "city": "Anytown",
        "province": "State",
        "postalcode": "12345",
        "country": "USA",
        "active": true
      }
]